bkm10_lib/__init__.py
bkm10_lib/backend.py
bkm10_lib/cff_inputs.py
bkm10_lib/constants.py
bkm10_lib/core.py
bkm10_lib/formalism.py
bkm10_lib/inputs.py
bkm10_lib/validation.py
tests/__init__.py
tests/test_bh_unpolarized_coefficients.py
tests/test_dvcs_polarized_coefficients.py
tests/test_dvcs_unpolarized_coefficients.py
tests/test_interference_polarized_coefficients.py
tests/test_interference_unpolarized_coefficients.py
bkm10-2.0.1.dist-info/METADATA
bkm10-2.0.1.dist-info/WHEEL
bkm10-2.0.1.dist-info/top_level.txt
bkm10-2.0.1.dist-info/RECORD
