Metadata-Version: 2.4
Name: bkm10
Version: 2.0.1
Summary: A formalism for computing DVCS cross sections using the BKM10 approach.
Home-page: https://github.com/Woofmagic/bkm10_lib
Author: Woofmagic
Author-email: Woofmagic <none@none.com>
License: MIT
Project-URL: homepage, https://github.com/woofmagic/bkm10_lib
Project-URL: documentation, https://github.com/Woofmagic/bkm10_lib/blob/main/README.md
Classifier: Intended Audience :: Science/Research
Classifier: Intended Audience :: Developers
Classifier: Programming Language :: Python
Requires-Python: >=3.7
Requires-Dist: numpy
Requires-Dist: matplotlib
Dynamic: author
Dynamic: home-page
Dynamic: requires-python
